wofkfff/__init__.py
wofkfff/core.py
wofkfff/log.py
wofkfff/server.py
wofkfff-0.1.1.dist-info/METADATA
wofkfff-0.1.1.dist-info/WHEEL
wofkfff-0.1.1.dist-info/top_level.txt
wofkfff-0.1.1.dist-info/RECORD
